[
  { "season_year": 2025, "race_number": 1, "race_name": "Daytona 500", "short_name": "DAY", "race_date": "2025-02-16", "stage": "season" },
  { "season_year": 2025, "race_number": 2, "race_name": "Atlanta", "short_name": "ATL", "race_date": "2025-02-23", "stage": "season" },
  { "season_year": 2025, "race_number": 3, "race_name": "Circuit of the Americas", "short_name": "COTA", "race_date": "2025-03-02", "stage": "season" },
  { "season_year": 2025, "race_number": 4, "race_name": "Phoenix", "short_name": "PHO", "race_date": "2025-03-09", "stage": "season" },
  { "season_year": 2025, "race_number": 5, "race_name": "Las Vegas", "short_name": "LVS", "race_date": "2025-03-16", "stage": "season" },
  { "season_year": 2025, "race_number": 6, "race_name": "Homestead-Miami", "short_name": "HOM", "race_date": "2025-03-23", "stage": "season" },
  { "season_year": 2025, "race_number": 7, "race_name": "Martinsville", "short_name": "MAR", "race_date": "2025-03-30", "stage": "season" },
  { "season_year": 2025, "race_number": 8, "race_name": "Darlington", "short_name": "DAR", "race_date": "2025-04-06", "stage": "season" },
  { "season_year": 2025, "race_number": 9, "race_name": "Bristol", "short_name": "BRI", "race_date": "2025-04-13", "stage": "season" },
  { "season_year": 2025, "race_number": 10, "race_name": "Talladega", "short_name": "TAL", "race_date": "2025-04-27", "stage": "season" },
  { "season_year": 2025, "race_number": 11, "race_name": "Texas", "short_name": "TEX", "race_date": "2025-05-04", "stage": "season" },
  { "season_year": 2025, "race_number": 12, "race_name": "Kansas", "short_name": "KAN", "race_date": "2025-05-11", "stage": "season" },
  { "season_year": 2025, "race_number": 13, "race_name": "Charlotte", "short_name": "CLT", "race_date": "2025-05-25", "stage": "season" },
  { "season_year": 2025, "race_number": 14, "race_name": "Nashville", "short_name": "NSH", "race_date": "2025-06-01", "stage": "season" },
  { "season_year": 2025, "race_number": 15, "race_name": "Michigan", "short_name": "MCH", "race_date": "2025-06-08", "stage": "season" },
  { "season_year": 2025, "race_number": 16, "race_name": "Mexico City", "short_name": "MEX", "race_date": "2025-06-15", "stage": "season" },
  { "season_year": 2025, "race_number": 17, "race_name": "Pocono", "short_name": "POC", "race_date": "2025-06-22", "stage": "season" },
  { "season_year": 2025, "race_number": 18, "race_name": "Atlanta", "short_name": "ATL", "race_date": "2025-06-28", "stage": "season" },
  { "season_year": 2025, "race_number": 19, "race_name": "Chicago", "short_name": "CHI", "race_date": "2025-07-06", "stage": "season" },
  { "season_year": 2025, "race_number": 20, "race_name": "Sonoma", "short_name": "SON", "race_date": "2025-07-13", "stage": "season" },
  { "season_year": 2025, "race_number": 21, "race_name": "Dover", "short_name": "DOV", "race_date": "2025-07-20", "stage": "season" },
  { "season_year": 2025, "race_number": 22, "race_name": "Indianapolis", "short_name": "IND", "race_date": "2025-07-27", "stage": "season" },
  { "season_year": 2025, "race_number": 23, "race_name": "Iowa", "short_name": "IOWA", "race_date": "2025-08-03", "stage": "season" },
  { "season_year": 2025, "race_number": 24, "race_name": "Watkins Glen", "short_name": "GLEN", "race_date": "2025-08-10", "stage": "season" },
  { "season_year": 2025, "race_number": 25, "race_name": "Richmond", "short_name": "RCH", "race_date": "2025-08-16", "stage": "season" },
  { "season_year": 2025, "race_number": 26, "race_name": "Daytona", "short_name": "DAY", "race_date": "2025-08-23", "stage": "season" },
  { "season_year": 2025, "race_number": 27, "race_name": "Darlington", "short_name": "DAR", "race_date": "2025-08-31", "stage": "playoff_16" },
  { "season_year": 2025, "race_number": 28, "race_name": "Gateway", "short_name": "GTW", "race_date": "2025-09-07", "stage": "playoff_16" },
  { "season_year": 2025, "race_number": 29, "race_name": "Bristol", "short_name": "BRI", "race_date": "2025-09-13", "stage": "playoff_16" },
  { "season_year": 2025, "race_number": 30, "race_name": "New Hampshire", "short_name": "NHA", "race_date": "2025-09-21", "stage": "playoff_12" },
  { "season_year": 2025, "race_number": 31, "race_name": "Kansas", "short_name": "KAN", "race_date": "2025-09-28", "stage": "playoff_12" },
  { "season_year": 2025, "race_number": 32, "race_name": "Charlotte RC", "short_name": "ROV", "race_date": "2025-10-05", "stage": "playoff_12" },
  { "season_year": 2025, "race_number": 33, "race_name": "Las Vegas", "short_name": "LVS", "race_date": "2025-10-12", "stage": "playoff_8" },
  { "season_year": 2025, "race_number": 34, "race_name": "Talladega", "short_name": "TAL", "race_date": "2025-10-19", "stage": "playoff_8" },
  { "season_year": 2025, "race_number": 35, "race_name": "Martinsville", "short_name": "MAR", "race_date": "2025-10-26", "stage": "playoff_8" },
  { "season_year": 2025, "race_number": 36, "race_name": "Phoenix", "short_name": "PHO", "race_date": "2025-11-02", "stage": "playoff_4" },
  { "season_year": 2024, "race_number": 1, "race_name": "Daytona 500", "short_name": "DAY", "race_date": "2024-02-19", "stage": "season" },
  { "season_year": 2024, "race_number": 2, "race_name": "Atlanta", "short_name": "ATL", "race_date": "2024-02-25", "stage": "season" },
  { "season_year": 2024, "race_number": 3, "race_name": "Las Vegas", "short_name": "LVS", "race_date": "2024-03-03", "stage": "season" },
  { "season_year": 2024, "race_number": 4, "race_name": "Phoenix", "short_name": "PHO", "race_date": "2024-03-10", "stage": "season" },
  { "season_year": 2024, "race_number": 5, "race_name": "Bristol", "short_name": "BRI", "race_date": "2024-03-17", "stage": "season" },
  { "season_year": 2024, "race_number": 6, "race_name": "Circuit of the Americas", "short_name": "COTA", "race_date": "2024-03-24", "stage": "season" },
  { "season_year": 2024, "race_number": 7, "race_name": "Richmond", "short_name": "RCH", "race_date": "2024-03-31", "stage": "season" },
  { "season_year": 2024, "race_number": 8, "race_name": "Martinsville", "short_name": "MAR", "race_date": "2024-04-07", "stage": "season" },
  { "season_year": 2024, "race_number": 9, "race_name": "Texas", "short_name": "TEX", "race_date": "2024-04-14", "stage": "season" },
  { "season_year": 2024, "race_number": 10, "race_name": "Talladega", "short_name": "TAL", "race_date": "2024-04-21", "stage": "season" },
  { "season_year": 2024, "race_number": 11, "race_name": "Dover", "short_name": "DOV", "race_date": "2024-04-28", "stage": "season" },
  { "season_year": 2024, "race_number": 12, "race_name": "Kansas", "short_name": "KAN", "race_date": "2024-05-05", "stage": "season" },
  { "season_year": 2024, "race_number": 13, "race_name": "Darlington", "short_name": "DAR", "race_date": "2024-05-12", "stage": "season" },
  { "season_year": 2024, "race_number": 14, "race_name": "Charlotte", "short_name": "CLT", "race_date": "2024-05-26", "stage": "season" },
  { "season_year": 2024, "race_number": 15, "race_name": "Gateway", "short_name": "GTW", "race_date": "2024-06-02", "stage": "season" },
  { "season_year": 2024, "race_number": 16, "race_name": "Sonoma", "short_name": "SON", "race_date": "2024-06-09", "stage": "season" },
  { "season_year": 2024, "race_number": 17, "race_name": "Iowa", "short_name": "IOWA", "race_date": "2024-06-16", "stage": "season" },
  { "season_year": 2024, "race_number": 18, "race_name": "New Hampshire", "short_name": "NHA", "race_date": "2024-06-23", "stage": "season" },
  { "season_year": 2024, "race_number": 19, "race_name": "Nashville", "short_name": "NSH", "race_date": "2024-06-30", "stage": "season" },
  { "season_year": 2024, "race_number": 20, "race_name": "Chicago", "short_name": "CHI", "race_date": "2024-07-07", "stage": "season" },
  { "season_year": 2024, "race_number": 21, "race_name": "Pocono", "short_name": "POC", "race_date": "2024-07-14", "stage": "season" },
  { "season_year": 2024, "race_number": 22, "race_name": "Indianapolis", "short_name": "IND", "race_date": "2024-07-21", "stage": "season" },
  { "season_year": 2024, "race_number": 23, "race_name": "Richmond", "short_name": "RCH", "race_date": "2024-08-11", "stage": "season" },
  { "season_year": 2024, "race_number": 24, "race_name": "Michigan", "short_name": "MCH", "race_date": "2024-08-18", "stage": "season" },
  { "season_year": 2024, "race_number": 25, "race_name": "Daytona", "short_name": "DAY", "race_date": "2024-08-24", "stage": "season" },
  { "season_year": 2024, "race_number": 26, "race_name": "Darlington", "short_name": "DAR", "race_date": "2024-09-01", "stage": "season" },
  { "season_year": 2024, "race_number": 27, "race_name": "Atlanta", "short_name": "ATL", "race_date": "2024-09-08", "stage": "playoff_16" },
  { "season_year": 2024, "race_number": 28, "race_name": "Watkins Glen", "short_name": "GLEN", "race_date": "2024-09-15", "stage": "playoff_16" },
  { "season_year": 2024, "race_number": 29, "race_name": "Bristol", "short_name": "BRI", "race_date": "2024-09-21", "stage": "playoff_16" },
  { "season_year": 2024, "race_number": 30, "race_name": "Kansas", "short_name": "KAN", "race_date": "2024-09-29", "stage": "playoff_12" },
  { "season_year": 2024, "race_number": 31, "race_name": "Talladega", "short_name": "TAL", "race_date": "2024-10-06", "stage": "playoff_12" },
  { "season_year": 2024, "race_number": 32, "race_name": "Charlotte RC", "short_name": "ROV", "race_date": "2024-10-13", "stage": "playoff_12" },
  { "season_year": 2024, "race_number": 33, "race_name": "Las Vegas", "short_name": "LVS", "race_date": "2024-10-20", "stage": "playoff_8" },
  { "season_year": 2024, "race_number": 34, "race_name": "Homestead-Miami", "short_name": "HOM", "race_date": "2024-10-27", "stage": "playoff_8" },
  { "season_year": 2024, "race_number": 35, "race_name": "Martinsville", "short_name": "MAR", "race_date": "2024-11-03", "stage": "playoff_8" },
  { "season_year": 2024, "race_number": 36, "race_name": "Phoenix", "short_name": "PHO", "race_date": "2024-11-10", "stage": "playoff_4" }
]